Workbook
Name Slicer_Category: #N/A
Name Slicer_Month: #N/A
Name Slicer_Product: #N/A
Name Slicer_Product1: #N/A
Name Slicer_Store_Location: #N/A

Sheet Uncleaned Data
A1: Transaction_ID | B1: Date | C1: Time | D1: Customer_Name | E1: Customer_ID | F1: Customer_Type | G1: Product | H1: Category | I1: Temperature | J1: Size | K1: Quantity | L1: Unit_Price | M1: Discount | N1: Gross_Sales | O1: Net_Sales | P1: Payment_Method | Q1: Sales_Channel | R1: Store_Location | S1: Staff_Name | T1: Order_Status | U1: Customer_Rating | V1: Loyalty_Points | W1: Delivery_Minutes | X1: Cost_Per_Item | Y1: Profit | Z1: Campaign | AA1: Feedback | AB1: Calculated_Gross_Sales | AC1: Discount_Amount | AD1: Calculated_Net_Sales | AE1: Total_Cost | AF1: Calculated_Profit | AG1: Year | AH1: Month_Number | AI1: Month | AJ1: Day
A2: TXN-00001 | B2: 45553 | C2: 10:20 | D2: Simran Gupta | E2: CUST0310 | F2: New Customer | G2: Cappuccino | H2: Coffee | I2: Hot | K2: 2 | L2: 130 | N2: 260 | P2: Card | Q2: Walk-in | R2: Bengaluru | S2: Neha | T2: Completed | U2: 2 | V2: 233 | W2: 56 | X2: 56.78 | Z2: Unknown | AA2: Excellent | AB2: 260 | AC2: 0 | AD2: 260 | AE2: 113.56 | AF2: 146.44 | AG2: 2024 | AH2: 9 | AI2: Sep | AJ2: Wednesday
A3: TXN-00002 | B3: 45517 | C3: 17:15 | D3: Sneha Kaur | E3: CUST0395 | F3: Unknown | G3: Brownie | H3: Bakery | I3: Food | J3: Medium | K3: 1 | L3: 115 | M3: 0.05 | N3: 115 | O3: 109.25 | P3: Card | Q3: Walk-in | R3: Bengaluru | S3: Rahul | T3: Completed | U3: 4 | V3: 304 | X3: 59.12 | Y3: 50.13 | Z3: Student Offer | AA3: Unknown | AB3: 115 | AC3: 5.75 | AD3: 109.25 | AE3: 59.12 | AF3: 50.13 | AG3: 2024 | AH3: 8 | AI3: Aug | AJ3: Tuesday
A4: TXN-00003 | B4: 45293 | C4: 10:00 | D4: Sahil Singh | E4: CUST0330 | F4: Member | G4: Cookies | H4: Bakery | I4: Food | J4: Medium | K4: 1 | L4: 70 | N4: 70 | P4: Cash | Q4: Walk-in | R4: Mohali | S4: Karan | T4: Completed | V4: 237 | X4: 24.95 | Z4: Weekend Offer | AA4: Poor | AB4: 70 | AC4: 0 | AD4: 70 | AE4: 24.95 | AF4: 45.05 | AG4: 2024 | AH4: 1 | AI4: Jan | AJ4: Tuesday
A5: TXN-00004 | B5: 45335 | C5: 09:10 | D5: Rahul Bansal | E5: CUST0134 | F5: Member | G5: Latte | H5: Coffee | I5: Hot | J5: Large | K5: 1 | L5: 120 | M5: 0.1 | N5: 120 | O5: 108 | P5: Card | R5: Ludhiana | S5: Priya | T5: Completed | U5: 2 | V5: 162 | X5: 54.9 | Y5: 53.1 | Z5: Unknown | AA5: Average | AB5: 120 | AC5: 12 | AD5: 108 | AE5: 54.9 | AF5: 53.1 | AG5: 2024 | AH5: 2 | AI5: Feb | AJ5: Tuesday
A6: TXN-00005 | B6: 45530 | C6: 19:30 | D6: Sahil Chopra | E6: CUST0256 | F6: Unknown | G6: Iced Latte | H6: Coffee | I6: Cold | J6: Medium | K6: 1 | L6: 160 | M6: 0.1 | N6: 160 | O6: 144 | P6: UPI | Q6: Walk-in | R6: Ludhiana | S6: Neha | T6: Completed | U6: 1 | V6: 476 | X6: 57.6 | Y6: 86.4 | Z6: Weekend Offer | AA6: Excellent | AB6: 160 | AC6: 16 | AD6: 144 | AE6: 57.6 | AF6: 86.4 | AG6: 2024 | AH6: 8 | AI6: Aug | AJ6: Monday
A7: TXN-00006 | B7: 45460 | C7: 12:10 | D7: Arjun Chopra | E7: CUST0120 | F7: New Customer | G7: Green Tea | H7: Tea | I7: Hot | J7: Small | K7: 2 | L7: 100 | M7: 0.05 | N7: 200 | O7: 190 | P7: Cash | Q7: Walk-in | R7: Chandigarh | S7: Karan | T7: Completed | U7: 1 | V7: 200 | X7: 43.82 | Y7: 102.36 | Z7: Instagram | AA7: Good | AB7: 200 | AC7: 10 | AD7: 190 | AE7: 87.64 | AF7: 102.36 | AG7: 2024 | AH7: 6 | AI7: Jun | AJ7: Monday
A8: TXN-00007 | C8: 16:30 | D8: Rohan Bansal | E8: CUST0377 | F8: Unknown | G8: Cookies | H8: Bakery | I8: Food | J8: Small | K8: 2 | L8: 70 | N8: 140 | P8: Card | Q8: Walk-in | R8: Bengaluru | S8: Rahul | T8: Completed | U8: 1 | V8: 159 | W8: 47 | X8: 26.09 | Z8: Instagram | AA8: Average | AB8: 140 | AC8: 0 | AD8: 140 | AE8: 52.18 | AF8: 87.82
A9: TXN-00008 | B9: 45469 | C9: 14:30 | D9: Meera Malhotra | E9: CUST0197 | F9: Regular | G9: Americano | H9: Coffee | I9: Hot | J9: Medium | K9: 2 | L9: 100 | M9: 0.1 | N9: 200 | O9: 180 | P9: Cash | Q9: Walk-in | R9: Ludhiana | S9: Ananya | T9: Completed | U9: 5 | V9: 158 | W9: 16 | X9: 40.53 | Y9: 98.94 | Z9: Unknown | AA9: Poor | AB9: 200 | AC9: 20 | AD9: 180 | AE9: 81.06 | AF9: 98.94 | AG9: 2024 | AH9: 6 | AI9: Jun | AJ9: Wednesday
A10: TXN-00009 | B10: 45371 | C10: 14:10 | D10: Neha Malhotra | E10: CUST0395 | F10: Unknown | G10: Brownie | H10: Bakery | I10: Food | J10: Small | K10: 2 | L10: 120 | N10: 240 | P10: Card | Q10: Delivery App | R10: Mohali | S10: Rahul | T10: Completed | U10: 5 | V10: 134 | W10: 37 | X10: 63.46 | Z10: Unknown | AA10: Excellent | AB10: 240 | AC10: 0 | AD10: 240 | AE10: 126.92 | AF10: 113.08 | AG10: 2024 | AH10: 3 | AI10: Mar | AJ10: Wednesday
A11: TXN-00010 | B11: 45429 | C11: 16:50 | D11: Nikhil Gupta | E11: CUST0136 | F11: Regular | G11: Mocha | H11: Coffee | I11: Hot | J11: Small | K11: 1 | L11: 145 | M11: 0.05 | N11: 145 | O11: 137.75 | P11: Card | Q11: Online | R11: Delhi | S11: Simran | T11: Completed | U11: 1 | V11: 352 | W11: 33 | X11: 86.8 | Y11: 50.95 | Z11: Festive Offer | AA11: Average | AB11: 145 | AC11: 7.25 | AD11: 137.75 | AE11: 86.8 | AF11: 50.95 | AG11: 2024 | AH11: 5 | AI11: May | AJ11: Friday
A12: TXN-00011 | B12: 45477 | C12: 21:10 | D12: Kavya Verma | E12: CUST0394 | F12: Regular | G12: Mocha | H12: Coffee | I12: Hot | J12: Medium | K12: 1 | L12: 145 | M12: 0 | N12: 145 | O12: 145 | P12: Cash | Q12: Walk-in | R12: Mohali | S12: Rahul | T12: Completed | U12: 1 | V12: 403 | W12: 52 | X12: 54.97 | Y12: 90.03 | Z12: Weekend Offer | AA12: Good | AB12: 145 | AC12: 0 | AD12: 145 | AE12: 54.97 | AF12: 90.03 | AG12: 2024 | AH12: 7 | AI12: Jul | AJ12: Thursday
A13: TXN-00012 | B13: 45565 | C13: 08:50 | D13: Isha Chopra | E13: CUST0312 | F13: Regular | G13: Cold Brew | H13: Coffee | I13: Cold | J13: Medium | K13: 1 | L13: 160 | M13: 0.05 | N13: 160 | O13: 152 | P13: UPI | Q13: Delivery App | R13: Bengaluru | S13: Rohan | T13: Completed | U13: 5 | V13: 99 | W13: 12 | X13: 93.45 | Y13: 58.55 | Z13: Instagram | AA13: Average | AB13: 160 | AC13: 8 | AD13: 152 | AE13: 93.45 | AF13: 58.55 | AG13: 2024 | AH13: 9 | AI13: Sep | AJ13: Monday
A14: TXN-00013 | B14: 45387 | C14: 18:45 | D14: Riya Sharma | E14: CUST0328 | F14: Regular | G14: Masala Chai | H14: Tea | I14: Hot | J14: Large | K14: 3 | L14: 75 | M14: 0.05 | N14: 225 | O14: 213.75 | P14: Card | Q14: Walk-in | R14: Gurugram | S14: Priya | T14: Completed | U14: 4 | V14: 435 | W14: 44 | X14: 45.93 | Y14: 75.96 | Z14: Student Offer | AA14: Good | AB14: 225 | AC14: 11.25 | AD14: 213.75 | AE14: 137.79 | AF14: 75.96 | AG14: 2024 | AH14: 4 | AI14: Apr | AJ14: Friday
A15: TXN-00014 | B15: 45402 | C15: 10:50 | D15: Rohan Malhotra | E15: CUST0155 | F15: Regular | G15: Cappuccino | H15: Coffee | I15: Hot | J15: Small | K15: 2 | L15: 140 | M15: 0.05 | N15: 280 | O15: 266 | P15: Cash | R15: Delhi | S15: Rohan | T15: Completed | U15: 4 | V15: 77 | W15: 18 | X15: 48.6 | Y15: 168.8 | Z15: Unknown | AA15: Average | AB15: 280 | AC15: 14 | AD15: 266 | AE15: 97.2 | AF15: 168.8 | AG15: 2024 | AH15: 4 | AI15: Apr | AJ15: Saturday
A16: TXN-00015 | B16: 45441 | C16: 16:20 | D16: Pooja Kaur | E16: CUST0197 | F16: Member | G16: Croissant | H16: Bakery | I16: Food | J16: Large | K16: 1 | L16: 95 | M16: 0.1 | N16: 95 | O16: 85.5 | P16: Card | Q16: Delivery App | R16: Bengaluru | S16: Priya | T16: Cancelled | U16: 5 | V16: 206 | W16: 40 | X16: 58.59 | Y16: 26.91 | Z16: Unknown | AA16: Excellent | AB16: 95 | AC16: 9.5 | AD16: 85.5 | AE16: 58.59 | AF16: 26.91 | AG16: 2024 | AH16: 5 | AI16: May | AJ16: Wednesday
A17: TXN-00016 | B17: 45371 | C17: 10:15 | D17: Riya Kapoor | E17: CUST0192 | F17: New Customer | G17: Espresso | H17: Coffee | I17: Hot | J17: Medium | K17: 2 | L17: 95 | M17: 0.15 | N17: 190 | O17: 161.5 | P17: Card | R17: Bengaluru | S17: Simran | T17: Cancelled | U17: 1 | V17: 17 | W17: 49 | X17: 34.9 | Y17: 91.7 | Z17: Weekend Offer | AA17: Good | AB17: 190 | AC17: 28.5 | AD17: 161.5 | AE17: 69.8 | AF17: 91.7 | AG17: 2024 | AH17: 3 | AI17: Mar | AJ17: Wednesday
A18: TXN-00017 | B18: 45426 | C18: 20:50 | D18: Pooja Kaur | E18: CUST0114 | F18: Regular | G18: Muffin | H18: Bakery | I18: Food | J18: Large | K18: 1 | L18: 85 | M18: 0.05 | N18: 85 | O18: 80.75 | P18: Cash | Q18: Delivery App | R18: Gurugram | S18: Karan | T18: Completed | U18: 3 | V18: 162 | W18: 43 | X18: 46.65 | Y18: 34.1 | Z18: Instagram | AA18: Excellent | AB18: 85 | AC18: 4.25 | AD18: 80.75 | AE18: 46.65 | AF18: 34.1 | AG18: 2024 | AH18: 5 | AI18: May | AJ18: Tuesday
A19: TXN-00018 | B19: 45309 | C19: 11:15 | D19: Sahil Singh | E19: CUST0286 | F19: Regular | G19: Cold Brew | H19: Coffee | I19: Cold | L19: 155 | M19: 0 | N19: 465 | O19: 465 | P19: Card | Q19: Delivery App | R19: Delhi | S19: Rohan | T19: Cancelled | U19: 4 | V19: 255 | W19: 43 | X19: 66.17 | Y19: 266.49 | Z19: Unknown | AA19: Good | AG19: 2024 | AH19: 1 | AI19: Jan | AJ19: Thursday
A20: TXN-00019 | B20: 45643 | C20: 10:20 | D20: Arjun Gupta | E20: CUST0320 | F20: Member | G20: Muffin | H20: Bakery | I20: Food | J20: Large | K20: 1 | L20: 90 | M20: 0.1 | N20: 90 | O20: 81 | P20: Card | Q20: Walk-in | R20: Chandigarh | S20: Simran | T20: Completed | V20: 269 | X20: 41.86 | Y20: 39.14 | Z20: Unknown | AA20: Excellent | AB20: 90 | AC20: 9 | AD20: 81 | AE20: 41.86 | AF20: 39.14 | AG20: 2024 | AH20: 12 | AI20: Dec | AJ20: Tuesday
A21: TXN-00020 | B21: 45544 | C21: 11:15 | D21: Isha Malhotra | E21: CUST0107 | F21: Regular | G21: Mocha | H21: Coffee | I21: Hot | J21: Medium | K21: 2 | L21: 155 | M21: 0.05 | N21: 310 | O21: 294.5 | P21: UPI | R21: Gurugram | S21: Ananya | T21: Pending | U21: 1 | V21: 468 | X21: 78.33 | Y21: 137.84 | Z21: Weekend Offer | AA21: Excellent | AB21: 310 | AC21: 15.5 | AD21: 294.5 | AE21: 156.66 | AF21: 137.84 | AG21: 2024 | AH21: 9 | AI21: Sep | AJ21: Monday
A22: TXN-00021 | B22: 45460 | C22: 18:30 | D22: Nikhil Kaur | E22: CUST0307 | F22: Regular | G22: Iced Latte | H22: Coffee | I22: Cold | K22: 4 | L22: 160 | N22: 640 | P22: Card | Q22: Walk-in | R22: Delhi | S22: Neha | T22: Completed | U22: 4 | V22: 13 | W22: 51 | X22: 82.51 | Z22: Instagram | AA22: Unknown | AB22: 640 | AC22: 0 | AD22: 640 | AE22: 330.04 | AF22: 309.96 | AG22: 2024 | AH22: 6 | AI22: Jun | AJ22: Monday
A23: TXN-00022 | B23: 45475 | C23: 07:20 | D23: Kavya Kaur | E23: CUST0253 | F23: Member | G23: Mocha | H23: Coffee | I23: Hot | J23: Medium | K23: 2 | L23: 150 | M23: 0.15 | N23: 300 | O23: 255 | Q23: Online | R23: Delhi | S23: Priya | T23: Completed | U23: 3 | V23: 271 | W23: 49 | X23: 61.6 | Y23: 131.8 | Z23: Student Offer | AA23: Good | AB23: 300 | AC23: 45 | AD23: 255 | AE23: 123.2 | AF23: 131.8 | AG23: 2024 | AH23: 7 | AI23: Jul | AJ23: Tuesday
A24: TXN-00023 | B24: 45585 | C24: 10:00 | D24: Unknown | E24: CUST0127 | F24: New Customer | G24: Cookies | H24: Bakery | I24: Food | J24: Medium | K24: 1 | L24: 70 | M24: 0 | N24: 70 | O24: 70 | P24: Cash | Q24: Online | R24: Gurugram | S24: Simran | T24: Completed | U24: 2 | V24: 436 | W24: 11 | X24: 38.36 | Y24: 31.64 | Z24: Instagram | AA24: Poor | AB24: 70 | AC24: 0 | AD24: 70 | AE24: 38.36 | AF24: 31.64 | AG24: 2024 | AH24: 10 | AI24: Oct | AJ24: Sunday
A25: TXN-00024 | B25: 45446 | C25: 09:00 | D25: Arjun Chopra | E25: CUST0355 | F25: New Customer | G25: Green Tea | H25: Tea | I25: Hot | J25: Large | K25: 1 | L25: 100 | M25: 0 | N25: 100 | O25: 100 | P25: Card | Q25: Walk-in | R25: Ludhiana | S25: Karan | T25: Completed | U25: 2 | V25: 397 | W25: 50 | X25: 39.28 | Y25: 60.72 | Z25: Festive Offer | AA25: Poor | AB25: 100 | AC25: 0 | AD25: 100 | AE25: 39.28 | AF25: 60.72 | AG25: 2024 | AH25: 6 | AI25: Jun | AJ25: Monday
A26: TXN-00025 | B26: 45299 | C26: 10:30 | D26: Kavya Mehta | E26: CUST0250 | F26: New Customer | G26: Cookies | H26: Bakery | I26: Food | J26: Small | K26: 2 | L26: 70 | M26: 0 | N26: 140 | O26: 140 | P26: UPI | R26: Mohali | S26: Simran | T26: Completed | U26: 5 | V26: 99 | W26: 17 | X26: 34.99 | Y26: 70.02 | Z26: Weekend Offer | AA26: Average | AB26: 140 | AC26: 0 | AD26: 140 | AE26: 69.98 | AF26: 70.02 | AG26: 2024 | AH26: 1 | AI26: Jan | AJ26: Monday
A27: TXN-00026 | B27: 45446 | C27: 09:00 | D27: Kavya Singh | E27: CUST0167 | F27: Regular | G27: Latte | H27: Coffee | I27: Hot | J27: Small | K27: 1 | L27: 130 | M27: 0 | N27: 130 | O27: 130 | P27: Card | Q27: Delivery App | R27: Pune | S27: Priya | T27: Completed | U27: 5 | V27: 113 | W27: 50 | X27: 68.91 | Y27: 61.09 | Z27: Unknown | AA27: Poor | AB27: 130 | AC27: 0 | AD27: 130 | AE27: 68.91 | AF27: 61.09 | AG27: 2024 | AH27: 6 | AI27: Jun | AJ27: Monday
A28: TXN-00027 | B28: 45457 | C28: 20:45 | D28: Meera Verma | E28: CUST0251 | F28: Regular | G28: Iced Tea | H28: Tea | I28: Cold | J28: Large | K28: 2 | L28: 110 | M28: 0.15 | N28: 220 | O28: 187 | P28: UPI | Q28: Walk-in | R28: Bengaluru | S28: Neha | T28: Completed | U28: 5 | V28: 353 | W28: 23 | X28: 48.74 | Y28: 89.52 | Z28: Unknown | AA28: Unknown | AB28: 220 | AC28: 33 | AD28: 187 | AE28: 97.48 | AF28: 89.52 | AG28: 2024 | AH28: 6 | AI28: Jun | AJ28: Friday
A29: TXN-00028 | B29: 45567 | C29: 21:30 | D29: Isha Singh | E29: CUST0279 | F29: Member | G29: Croissant | H29: Bakery | I29: Food | J29: Small | K29: 1 | L29: 105 | M29: 0 | N29: 105 | O29: 105 | P29: Cash | R29: Mohali | S29: Karan | T29: Completed | U29: 4 | V29: 177 | W29: 18 | X29: 55.43 | Y29: 49.57 | Z29: Unknown | AA29: Poor | AB29: 105 | AC29: 0 | AD29: 105 | AE29: 55.43 | AF29: 49.57 | AG29: 2024 | AH29: 10 | AI29: Oct | AJ29: Wednesday
A30: TXN-00029 | B30: 45598 | C30: 18:15 | D30: Rahul Sharma | E30: CUST0332 | F30: Regular | G30: Brownie | H30: Bakery | I30: Food | J30: Large | K30: 1 | L30: 130 | M30: 0.1 | N30: 130 | O30: 117 | P30: UPI | Q30: Online | R30: Chandigarh | S30: Ananya | T30: Pending | U30: 5 | V30: 174 | W30: 14 | X30: 57.9 | Y30: 59.1 | Z30: Instagram | AA30: Excellent | AB30: 130 | AC30: 13 | AD30: 117 | AE30: 57.9 | AF30: 59.1 | AG30: 2024 | AH30: 11 | AI30: Nov | AJ30: Saturday
A31: TXN-00030 | B31: 45636 | C31: 10:20 | D31: Riya Singh | E31: CUST0293 | F31: Unknown | G31: Espresso | H31: Coffee | I31: Hot | J31: Medium | K31: 1 | L31: 100 | M31: 0.1 | N31: 100 | O31: 90 | P31: Card | Q31: Online | R31: Mohali | S31: Neha | T31: Completed | U31: 3 | V31: 138 | W31: 18 | X31: 52.33 | Y31: 37.67 | Z31: Student Offer | AA31: Average | AB31: 100 | AC31: 10 | AD31: 90 | AE31: 52.33 | AF31: 37.67 | AG31: 2024 | AH31: 12 | AI31: Dec | AJ31: Tuesday
A32: TXN-00031 | B32: 45554 | C32: 12:20 | D32: Meera Kaur | E32: CUST0213 | F32: Regular | G32: Espresso | H32: Coffee | I32: Hot | K32: 2 | L32: 85 | M32: 0.1 | N32: 170 | O32: 153 | P32: UPI | Q32: Online | R32: Pune | S32: Rohan | T32: Completed | U32: 2 | V32: 349 | W32: 27 | X32: 49.46 | Y32: 54.08 | Z32: Instagram | AA32: Average | AB32: 170 | AC32: 17 | AD32: 153 | AE32: 98.92 | AF32: 54.08 | AG32: 2024 | AH32: 9 | AI32: Sep | AJ32: Thursday
A33: TXN-00032 | B33: 45516 | C33: 09:10 | D33: Aditya Kapoor | E33: CUST0200 | F33: Regular | G33: Masala Chai | H33: Tea | I33: Hot | J33: Large | K33: 1 | L33: 75 | M33: 0.15 | N33: 75 | O33: 63.75 | P33: UPI | R33: Ludhiana | S33: Aarav | T33: Completed | U33: 4 | V33: 400 | W33: 12 | X33: 42.47 | Y33: 21.28 | Z33: Instagram | AA33: Average | AB33: 75 | AC33: 11.25 | AD33: 63.75 | AE33: 42.47 | AF33: 21.28 | AG33: 2024 | AH33: 8 | AI33: Aug | AJ33: Monday
A34: TXN-00033 | B34: 45512 | C34: 12:45 | D34: Unknown | E34: CUST0178 | F34: New Customer | G34: Brownie | H34: Bakery | I34: Food | J34: Large | K34: 1 | L34: 115 | M34: 0 | N34: 115 | O34: 115 | P34: Card | Q34: Walk-in | R34: Mohali | S34: Rohan | T34: Completed | U34: 1 | V34: 115 | W34: 23 | X34: 57.83 | Y34: 57.17 | Z34: Student Offer | AA34: Excellent | AB34: 115 | AC34: 0 | AD34: 115 | AE34: 57.83 | AF34: 57.17 | AG34: 2024 | AH34: 8 | AI34: Aug | AJ34: Thursday
A35: TXN-00034 | B35: 45485 | C35: 08:00 | D35: Aditya Malhotra | E35: CUST0136 | F35: New Customer | G35: Latte | H35: Coffee | I35: Hot | J35: Large | K35: 1 | L35: 115 | M35: 0.1 | N35: 115 | O35: 103.5 | P35: UPI | Q35: Online | R35: Gurugram | S35: Rahul | T35: Completed | U35: 2 | V35: 472 | W35: 51 | X35: 50 | Y35: 53.5 | Z35: Instagram | AA35: Excellent | AB35: 115 | AC35: 11.5 | AD35: 103.5 | AE35: 50 | AF35: 53.5 | AG35: 2024 | AH35: 7 | AI35: Jul | AJ35: Friday
A36: TXN-00035 | B36: 45440 | C36: 16:15 | D36: Karan Malhotra | E36: CUST0292 | F36: Regular | G36: Muffin | H36: Bakery | I36: Food | J36: Medium | K36: 1 | L36: 85 | M36: 0.1 | N36: 85 | O36: 76.5 | P36: Cash | Q36: Walk-in | R36: Delhi | S36: Rahul | T36: Completed | U36: 2 | V36: 316 | W36: 15 | X36: 51.81 | Y36: 24.69 | Z36: Weekend Offer | AA36: Excellent | AB36: 85 | AC36: 8.5 | AD36: 76.5 | AE36: 51.81 | AF36: 24.69 | AG36: 2024 | AH36: 5 | AI36: May | AJ36: Tuesday
A37: TXN-00036 | B37: 45482 | C37: 15:30 | D37: Kavya Malhotra | E37: CUST0170 | F37: New Customer | G37: Cappuccino | H37: Coffee | I37: Hot | J37: Large | K37: 3 | L37: 130 | M37: 0.1 | N37: 390 | O37: 351 | P37: UPI | Q37: Delivery App | R37: Chandigarh | S37: Rohan | T37: Completed | U37: 4 | V37: 257 | W37: 24 | X37: 46.02 | Y37: 212.94 | Z37: Unknown | AA37: Average | AB37: 390 | AC37: 39 | AD37: 351 | AE37: 138.06 | AF37: 212.94 | AG37: 2024 | AH37: 7 | AI37: Jul | AJ37: Tuesday
A38: TXN-00037 | B38: 45438 | C38: 07:20 | D38: Rohan Kapoor | E38: CUST0222 | F38: New Customer | G38: Latte | H38: Coffee | I38: Hot | J38: Medium | K38: 1 | L38: 120 | M38: 0.1 | O38: 108 | P38: Cash | Q38: Walk-in | R38: Delhi | S38: Aarav | T38: Cancelled | U38: 5 | V38: 385 | X38: 55.9 | Y38: 52.1 | Z38: Instagram | AA38: Excellent | AB38: 120 | AC38: 12 | AD38: 108 | AE38: 55.9 | AF38: 52.1 | AG38: 2024 | AH38: 5 | AI38: May | AJ38: Sunday
A39: TXN-00038 | B39: 45587 | C39: 17:10 | D39: Karan Gupta | E39: CUST0194 | F39: Unknown | G39: Cappuccino | H39: Coffee | I39: Hot | J39: Medium | K39: 5 | L39: 125 | M39: 0 | N39: 625 | O39: 625 | P39: UPI | Q39: Walk-in | R39: Chandigarh | S39: Rahul | T39: Completed | U39: 2 | V39: 271 | X39: 65.65 | Y39: 296.75 | Z39: Unknown | AA39: Unknown | AB39: 625 | AC39: 0 | AD39: 625 | AE39: 328.25 | AF39: 296.75 | AG39: 2024 | AH39: 10 | AI39: Oct | AJ39: Tuesday
A40: TXN-00039 | B40: 45378 | C40: 20:10 | D40: Sneha Mehta | E40: CUST0172 | F40: Regular | G40: Cookies | H40: Bakery | I40: Food | K40: 1 | L40: 70 | M40: 0.1 | N40: 70 | O40: 63 | P40: UPI | Q40: Delivery App | R40: Delhi | S40: Priya | T40: Completed | U40: 5 | V40: 112 | W40: 52 | X40: 29.02 | Y40: 33.98 | Z40: Weekend Offer | AA40: Average | AB40: 70 | AC40: 7 | AD40: 63 | AE40: 29.02 | AF40: 33.98 | AG40: 2024 | AH40: 3 | AI40: Mar | AJ40: Wednesday
A41: TXN-00040 | B41: 45631 | C41: 13:00 | D41: Arjun Singh | E41: CUST0171 | F41: Regular | G41: Sandwich | H41: Food | I41: Food | J41: Large | K41: 2 | L41: 180 | M41: 0.05 | N41: 360 | O41: 342 | P41: Card | Q41: Online | R41: Bengaluru | S41: Rahul | T41: Completed | U41: 2 | V41: 268 | X41: 106.83 | Y41: 128.34 | Z41: Instagram | AA41: Excellent | AB41: 360 | AC41: 18 | AD41: 342 | AE41: 213.66 | AF41: 128.34 | AG41: 2024 | AH41: 12 | AI41: Dec | AJ41: Thursday
A42: TXN-00041 | B42: 45424 | C42: 19:30 | D42: Rahul Gupta | E42: CUST0362 | F42: New Customer | G42: Green Tea | H42: Tea | I42: Hot | J42: Small | K42: 1 | L42: 105 | M42: 0.15 | N42: 105 | O42: 89.25 | P42: Card | Q42: Online | R42: Bengaluru | S42: Karan | T42: Cancelled | V42: 153 | W42: 55 | X42: 51.74 | Y42: 37.51 | Z42: Student Offer | AA42: Poor | AB42: 105 | AC42: 15.75 | AD42: 89.25 | AE42: 51.74 | AF42: 37.51 | AG42: 2024 | AH42: 5 | AI42: May | AJ42: Sunday
A43: TXN-00042 | B43: 45292 | C43: 10:30 | D43: Kavya Verma | E43: CUST0167 | F43: Regular | G43: Cold Brew | H43: Coffee | I43: Cold | J43: Large | K43: 1 | L43: 170 | M43: 0 | N43: 170 | O43: 170 | P43: UPI | Q43: Online | R43: Pune | S43: Priya | T43: Cancelled | U43: 1 | V43: 482 | W43: 27 | X43: 95 | Y43: 75 | Z43: Festive Offer | AA43: Good | AB43: 170 | AC43: 0 | AD43: 170 | AE43: 95 | AF43: 75 | AG43: 2024 | AH43: 1 | AI43: Jan | AJ43: Monday
A44: TXN-00043 | B44: 45426 | C44: 13:30 | D44: Neha Gupta | E44: CUST0368 | F44: Member | G44: Croissant | H44: Bakery | I44: Food | J44: Large | K44: 2 | L44: 95 | N44: 190 | P44: UPI | Q44: Online | R44: Bengaluru | S44: Aarav | T44: Cancelled | U44: 4 | V44: 109 | W44: 49 | X44: 49.11 | Z44: Festive Offer | AA44: Excellent | AB44: 190 | AC44: 0 | AD44: 190 | AE44: 98.22 | AF44: 91.78 | AG44: 2024 | AH44: 5 | AI44: May | AJ44: Tuesday
A45: TXN-00044 | B45: 45624 | C45: 11:10 | D45: Meera Malhotra | E45: CUST0344 | F45: Regular | G45: Cold Brew | H45: Coffee | I45: Cold | J45: Medium | K45: 1 | L45: 155 | N45: 155 | P45: Cash | Q45: Delivery App | R45: Gurugram | S45: Rahul | T45: Completed | V45: 324 | W45: 24 | X45: 61.87 | Z45: Instagram | AA45: Unknown | AB45: 155 | AC45: 0 | AD45: 155 | AE45: 61.87 | AF45: 93.13 | AG45: 2024 | AH45: 11 | AI45: Nov | AJ45: Thursday
A46: TXN-00045 | C46: 17:20 | D46: Meera Chopra | E46: CUST0232 | F46: Unknown | G46: Masala Chai | H46: Tea | I46: Hot | J46: Large | K46: 2 | L46: 90 | M46: 0.05 | N46: 180 | O46: 171 | P46: UPI | Q46: Walk-in | R46: Pune | S46: Ananya | T46: Completed | U46: 2 | V46: 7 | X46: 30.56 | Y46: 109.88 | Z46: Unknown | AA46: Poor | AB46: 180 | AC46: 9 | AD46: 171 | AE46: 61.12 | AF46: 109.88
A47: TXN-00046 | B47: 45573 | C47: 20:10 | D47: Pooja Sharma | E47: CUST0234 | F47: Regular | G47: Mocha | H47: Coffee | I47: Hot | J47: Large | K47: 2 | L47: 140 | M47: 0 | N47: 280 | O47: 280 | P47: UPI | Q47: Online | R47: Delhi | S47: Rahul | T47: Completed | V47: 495 | X47: 72.13 | Y47: 135.74 | Z47: Student Offer | AA47: Excellent | AB47: 280 | AC47: 0 | AD47: 280 | AE47: 144.26 | AF47: 135.74 | AG47: 2024 | AH47: 10 | AI47: Oct | AJ47: Tuesday
A48: TXN-00047 | B48: 45510 | C48: 15:30 | D48: Aarav Bansal | E48: CUST0397 | F48: Regular | G48: Cookies | H48: Bakery | I48: Food | K48: 1 | L48: 70 | M48: 0.15 | N48: 70 | O48: 59.5 | P48: Cash | Q48: Walk-in | R48: Pune | S48: Rohan | T48: Completed | U48: 4 | V48: 292 | X48: 34.54 | Y48: 24.96 | Z48: Unknown | AA48: Excellent | AB48: 70 | AC48: 10.5 | AD48: 59.5 | AE48: 34.54 | AF48: 24.96 | AG48: 2024 | AH48: 8 | AI48: Aug | AJ48: Tuesday
A49: TXN-00048 | B49: 45352 | C49: 21:15 | D49: Manish Bansal | E49: CUST0139 | F49: Regular | G49: Mocha | H49: Coffee | I49: Hot | J49: Large | K49: 2 | L49: 145 | M49: 0.1 | N49: 290 | O49: 261 | P49: UPI | Q49: Delivery App | R49: Ludhiana | S49: Priya | T49: Pending | U49: 3 | V49: 101 | W49: 37 | X49: 71.42 | Y49: 118.16 | Z49: Unknown | AA49: Unknown | AB49: 290 | AC49: 29 | AD49: 261 | AE49: 142.84 | AF49: 118.16 | AG49: 2024 | AH49: 3 | AI49: Mar | AJ49: Friday
A50: TXN-00049 | B50: 45507 | C50: 19:45 | D50: Rohan Chopra | E50: Unknown | F50: New Customer | G50: Latte | H50: Coffee | I50: Hot | J50: Small | K50: 2 | L50: 120 | M50: 0.1 | N50: 240 | O50: 216 | P50: UPI | Q50: Delivery App | R50: Gurugram | S50: Neha | T50: Cancelled | U50: 3 | W50: 20 | X50: 53.75 | Y50: 108.5 | Z50: Weekend Offer | AA50: Excellent | AB50: 240 | AC50: 24 | AD50: 216 | AE50: 107.5 | AF50: 108.5 | AG50: 2024 | AH50: 8 | AI50: Aug | AJ50: Saturday
A51: TXN-00050 | B51: 45377 | C51: 12:45 | D51: Rahul Kapoor | E51: CUST0325 | F51: Member | G51: Cappuccino | H51: Coffee | I51: Hot | J51: Large | K51: 2 | L51: 125 | M51: 0 | N51: 250 | O51: 250 | P51: UPI | R51: Delhi | S51: Rahul | T51: Cancelled | U51: 1 | V51: 397 | W51: 28 | X51: 62.11 | Y51: 125.78 | Z51: Instagram | AA51: Excellent | AB51: 250 | AC51: 0 | AD51: 250 | AE51: 124.22 | AF51: 125.78 | AG51: 2024 | AH51: 3 | AI51: Mar | AJ51: Tuesday
A52: TXN-00051 | B52: 45309 | C52: 18:50 | D52: Rahul Gupta | E52: CUST0319 | F52: Member | G52: Green Tea | H52: Tea | I52: Hot | J52: Small | K52: 2 | L52: 105 | M52: 0.05 | N52: 210 | O52: 199.5 | P52: Cash | Q52: Walk-in | R52: Gurugram | S52: Ananya | T52: Completed | V52: 207 | W52: 11 | X52: 47.93 | Y52: 103.64 | Z52: Unknown | AA52: Unknown | AB52: 210 | AC52: 10.5 | AD52: 199.5 | AE52: 95.86 | AF52: 103.64 | AG52: 2024 | AH52: 1 | AI52: Jan | AJ52: Thursday
A53: TXN-00052 | B53: 45644 | C53: 17:00 | D53: Kavya Verma | E53: CUST0328 | F53: Member | G53: Espresso | H53: Coffee | I53: Hot | J53: Medium | K53: 1 | L53: 100 | M53: 0 | N53: 100 | O53: 100 | P53: UPI | Q53: Walk-in | R53: Chandigarh | S53: Priya | T53: Cancelled | V53: 381 | X53: 45.72 | Y53: 54.28 | Z53: Student Offer | AA53: Good | AB53: 100 | AC53: 0 | AD53: 100 | AE53: 45.72 | AF53: 54.28 | AG53: 2024 | AH53: 12 | AI53: Dec | AJ53: Wednesday
A54: TXN-00053 | B54: 45541 | C54: 08:50 | D54: Isha Malhotra | E54: CUST0198 | F54: Regular | G54: Mocha | H54: Coffee | I54: Hot | J54: Medium | K54: 3 | L54: 150 | M54: 0 | N54: 450 | O54: 450 | P54: UPI | Q54: Walk-in | R54: Ludhiana | S54: Rohan | T54: Completed | V54: 490 | W54: 29 | X54: 67.63 | Y54: 247.11 | Z54: Instagram | AA54: Good | AB54: 450 | AC54: 0 | AD54: 450 | AE54: 202.89 | AF54: 247.11 | AG54: 2024 | AH54: 9 | AI54: Sep | AJ54: Friday
A55: TXN-00054 | B55: 45348 | C55: 19:45 | D55: Pooja Mehta | E55: CUST0222 | F55: New Customer | G55: Cappuccino | H55: Coffee | I55: Hot | K55: 3 | L55: 140 | M55: 0.1 | N55: 420 | O55: 378 | P55: UPI | Q55: Walk-in | R55: Gurugram | S55: Simran | T55: Completed | U55: 2 | V55: 385 | W55: 54 | X55: 68.28 | Y55: 173.16 | Z55: Unknown | AA55: Good | AB55: 420 | AC55: 42 | AD55: 378 | AE55: 204.84 | AF55: 173.16 | AG55: 2024 | AH55: 2 | AI55: Feb | AJ55: Monday
A56: TXN-00055 | B56: 45388 | C56: 08:15 | D56: Aarav Kaur | E56: CUST0338 | F56: Unknown | G56: Cheesecake | H56: Dessert | I56: Food | J56: Large | K56: 1 | L56: 190 | M56: 0.1 | N56: 190 | O56: 171 | P56: Cash | Q56: Online | R56: Pune | S56: Rohan | T56: Completed | U56: 5 | V56: 379 | W56: 43 | X56: 72.86 | Y56: 98.14 | Z56: Unknown | AA56: Poor | AB56: 190 | AC56: 19 | AD56: 171 | AE56: 72.86 | AF56: 98.14 | AG56: 2024 | AH56: 4 | AI56: Apr | AJ56: Saturday
A57: TXN-00056 | B57: 45407 | C57: 08:00 | D57: Rohan Bansal | E57: CUST0311 | F57: Unknown | G57: Cheesecake | H57: Dessert | I57: Food | K57: 1 | L57: 190 | M57: 0 | N57: 190 | O57: 190 | P57: UPI | Q57: Delivery App | R57: Pune | S57: Ananya | T57: Completed | U57: 2 | V57: 114 | W57: 52 | X57: 69.97 | Y57: 120.03 | Z57: Instagram | AA57: Good | AB57: 190 | AC57: 0 | AD57: 190 | AE57: 69.97 | AF57: 120.03 | AG57: 2024 | AH57: 4 | AI57: Apr | AJ57: Thursday
A58: TXN-00057 | B58: 45337 | C58: 21:20 | D58: Neha Malhotra | E58: CUST0180 | F58: Unknown | G58: Espresso | H58: Coffee | I58: Hot | J58: Small | K58: 1 | L58: 85 | M58: 0 | N58: 85 | O58: 85 | P58: UPI | Q58: Online | R58: Mohali | S58: Priya | T58: Cancelled | U58: 3 | V58: 382 | W58: 12 | X58: 39.6 | Y58: 45.4 | Z58: Instagram | AA58: Good | AB58: 85 | AC58: 0 | AD58: 85 | AE58: 39.6 | AF58: 45.4 | AG58: 2024 | AH58: 2 | AI58: Feb | AJ58: Thursday
A59: TXN-00058 | B59: 45372 | C59: 17:50 | D59: Sneha Gupta | E59: CUST0313 | F59: Unknown | G59: Espresso | H59: Coffee | I59: Hot | J59: Medium | K59: 1 | L59: 100 | M59: 0.1 | N59: 100 | O59: 90 | P59: UPI | Q59: Walk-in | R59: Mohali | S59: Simran | T59: Completed | U59: 2 | V59: 477 | W59: 37 | X59: 43.61 | Y59: 46.39 | Z59: Unknown | AA59: Average | AB59: 100 | AC59: 10 | AD59: 90 | AE59: 43.61 | AF59: 46.39 | AG59: 2024 | AH59: 3 | AI59: Mar | AJ59: Thursday
A60: TXN-00059 | B60: 45428 | C60: 10:00 | D60: Karan Chopra | E60: CUST0384 | F60: New Customer | G60: Latte | H60: Coffee | I60: Hot | J60: Large | K60: 3 | L60: 125 | N60: 375 | P60: Card | Q60: Online | R60: Gurugram | S60: Aarav | T60: Pending | V60: 42 | X60: 66.66 | Z60: Unknown | AA60: Unknown | AB60: 375 | AC60: 0 | AD60: 375 | AE60: 199.98 | AF60: 175.02 | AG60: 2024 | AH60: 5 | AI60: May | AJ60: Thursday
A61: TXN-00060 | B61: 45462 | C61: 08:30 | D61: Manish Sharma | E61: CUST0296 | F61: Member | G61: Cold Brew | H61: Coffee | I61: Cold | J61: Medium | K61: 2 | L61: 155 | M61: 0.05 | N61: 310 | O61: 294.5 | P61: Card | R61: Delhi | S61: Simran | T61: Cancelled | U61: 4 | V61: 295 | W61: 46 | X61: 89.18 | Y61: 116.14 | Z61: Festive Offer | AA61: Good | AB61: 310 | AC61: 15.5 | AD61: 294.5 | AE61: 178.36 | AF61: 116.14 | AG61: 2024 | AH61: 6 | AI61: Jun | AJ61: Wednesday
A62: TXN-00061 | B62: 45438 | C62: 08:45 | D62: Sahil Singh | E62: CUST0128 | F62: Regular | G62: Iced Tea | H62: Tea | I62: Cold | J62: Large | K62: 1 | L62: 110 | M62: 0.1 | N62: 110 | O62: 99 | P62: UPI | R62: Mohali | S62: Ananya | T62: Completed | U62: 2 | V62: 54 | W62: 39 | X62: 38.84 | Y62: 60.16 | Z62: Instagram | AA62: Poor | AB62: 110 | AC62: 11 | AD62: 99 | AE62: 38.84 | AF62: 60.16 | AG62: 2024 | AH62: 5 | AI62: May | AJ62: Sunday
A63: TXN-00062 | B63: 45564 | C63: 09:10 | D63: Karan Kaur | E63: CUST0289 | F63: Member | G63: Sandwich | H63: Food | I63: Food | J63: Medium | K63: 2 | L63: 175 | M63: 0 | N63: 350 | O63: 350 | P63: Cash | R63: Pune | S63: Neha | T63: Cancelled | V63: 155 | W63: 25 | X63: 85.63 | Y63: 178.74 | Z63: Unknown | AA63: Unknown | AB63: 350 | AC63: 0 | AD63: 350 | AE63: 171.26 | AF63: 178.74 | AG63: 2024 | AH63: 9 | AI63: Sep | AJ63: Sunday
A64: TXN-00063 | B64: 45574 | C64: 17:15 | D64: Rahul Mehta | E64: Unknown | F64: Regular | G64: Green Tea | H64: Tea | I64: Hot | J64: Medium | K64: 1 | L64: 90 | M64: 0.05 | N64: 90 | O64: 85.5 | P64: Card | Q64: Walk-in | R64: Pune | S64: Ananya | T64: Completed | V64: 54 | X64: 36.87 | Y64: 48.63 | Z64: Student Offer | AA64: Excellent | AB64: 90 | AC64: 4.5 | AD64: 85.5 | AE64: 36.87 | AF64: 48.63 | AG64: 2024 | AH64: 10 | AI64: Oct | AJ64: Wednesday
A65: TXN-00064 | B65: 45510 | C65: 21:45 | D65: Pooja Kapoor | E65: CUST0223 | F65: New Customer | G65: Espresso | H65: Coffee | I65: Hot | J65: Medium | K65: 1 | L65: 90 | M65: 0 | N65: 90 | O65: 90 | P65: UPI | Q65: Delivery App | R65: Gurugram | S65: Rohan | T65: Completed | U65: 3 | V65: 133 | X65: 44.61 | Y65: 45.39 | Z65: Instagram | AA65: Average | AB65: 90 | AC65: 0 | AD65: 90 | AE65: 44.61 | AF65: 45.39 | AG65: 2024 | AH65: 8 | AI65: Aug | AJ65: Tuesday
A66: TXN-00065 | B66: 45339 | C66: 15:50 | D66: Karan Mehta | E66: CUST0195 | F66: Regular | G66: Croissant | H66: Bakery | I66: Food | J66: Large | K66: 1 | L66: 100 | M66: 0.05 | N66: 100 | O66: 95 | P66: UPI | Q66: Delivery App | R66: Pune | S66: Aarav | T66: Completed | U66: 5 | V66: 100 | X66: 48.18 | Y66: 46.82 | Z66: Instagram | AA66: Average | AB66: 100 | AC66: 5 | AD66: 95 | AE66: 48.18 | AF66: 46.82 | AG66: 2024 | AH66: 2 | AI66: Feb | AJ66: Saturday
A67: TXN-00066 | B67: 45421 | C67: 11:20 | D67: Vivaan Singh | E67: CUST0170 | F67: Regular | G67: Iced Latte | H67: Coffee | I67: Cold | J67: Small | K67: 3 | L67: 155 | M67: 0 | N67: 465 | O67: 465 | P67: UPI | Q67: Delivery App | R67: Chandigarh | S67: Aarav | T67: Cancelled | U67: 3 | V67: 497 | W67: 53 | X67: 81.26 | Y67: 221.22 | Z67: Festive Offer | AA67: Average | AB67: 465 | AC67: 0 | AD67: 465 | AE67: 243.78 | AF67: 221.22 | AG67: 2024 | AH67: 5 | AI67: May | AJ67: Thursday
A68: TXN-00067 | B68: 45413 | C68: 09:30 | D68: Karan Malhotra | E68: CUST0355 | F68: New Customer | G68: Brownie | H68: Bakery | I68: Food | J68: Large | K68: 1 | L68: 120 | M68: 0.15 | N68: 120 | O68: 102 | Q68: Delivery App | R68: Bengaluru | S68: Ananya | T68: Cancelled | U68: 4 | W68: 17 | X68: 52.2 | Y68: 49.8 | Z68: Unknown | AA68: Poor | AB68: 120 | AC68: 18 | AD68: 102 | AE68: 52.2 | AF68: 49.8 | AG68: 2024 | AH68: 5 | AI68: May | AJ68: Wednesday
A69: TXN-00068 | B69: 45308 | C69: 20:00 | D69: Priya Kapoor | E69: CUST0205 | F69: Regular | G69: Green Tea | H69: Tea | I69: Hot | K69: 1 | L69: 95 | N69: 95 | P69: Card | Q69: Online | R69: Pune | S69: Rahul | T69: Pending | V69: 499 | X69: 43.29 | Z69: Festive Offer | AA69: Average | AB69: 95 | AC69: 0 | AD69: 95 | AE69: 43.29 | AF69: 51.71 | AG69: 2024 | AH69: 1 | AI69: Jan | AJ69: Wednesday
A70: TXN-00069 | B70: 45395 | C70: 07:15 | D70: Rohan Kaur | E70: CUST0182 | F70: New Customer | G70: Sandwich | H70: Food | I70: Food | J70: Large | K70: 2 | L70: 190 | M70: 0 | N70: 380 | O70: 380 | P70: UPI | Q70: Online | R70: Chandigarh | S70: Rahul | T70: Pending | U70: 2 | V70: 264 | W70: 36 | X70: 102.32 | Y70: 175.36 | Z70: Instagram | AA70: Excellent | AB70: 380 | AC70: 0 | AD70: 380 | AE70: 204.64 | AF70: 175.36 | AG70: 2024 | AH70: 4 | AI70: Apr | AJ70: Saturday
A71: TXN-00070 | B71: 45439 | C71: 12:30 | D71: Aarav Kapoor | E71: CUST0246 | F71: Member | G71: Cheesecake | H71: Dessert | I71: Food | J71: Medium | K71: 1 | L71: 200 | M71: 0 | N71: 200 | O71: 200 | P71: UPI | R71: Bengaluru | S71: Rahul | T71: Completed | U71: 4 | V71: 144 | W71: 14 | X71: 103.06 | Y71: 96.94 | Z71: Instagram | AA71: Excellent | AB71: 200 | AC71: 0 | AD71: 200 | AE71: 103.06 | AF71: 96.94 | AG71: 2024 | AH71: 5 | AI71: May | AJ71: Monday
A72: TXN-00071 | B72: 45597 | C72: 16:00 | D72: Sneha Kapoor | E72: CUST0235 | F72: Regular | G72: Iced Latte | H72: Coffee | I72: Cold | J72: Small | K72: 1 | L72: 160 | M72: 0.1 | N72: 160 | O72: 144 | P72: UPI | Q72: Online | R72: Delhi | S72: Karan | T72: Completed | U72: 2 | V72: 111 | W72: 12 | X72: 71.25 | Y72: 72.75 | Z72: Instagram | AA72: Excellent | AB72: 160 | AC72: 16 | AD72: 144 | AE72: 71.25 | AF72: 72.75 | AG72: 2024 | AH72: 11 | AI72: Nov | AJ72: Friday
A73: TXN-00072 | B73: 45438 | C73: 12:15 | D73: Pooja Verma | E73: CUST0143 | F73: Regular | G73: Brownie | H73: Bakery | I73: Food | J73: Large | K73: 1 | L73: 120 | M73: 0 | N73: 120 | O73: 120 | P73: UPI | Q73: Walk-in | R73: Mohali | S73: Rohan | T73: Pending | U73: 2 | V73: 216 | X73: 67.81 | Y73: 52.19 | Z73: Instagram | AA73: Unknown | AB73: 120 | AC73: 0 | AD73: 120 | AE73: 67.81 | AF73: 52.19 | AG73: 2024 | AH73: 5 | AI73: May | AJ73: Sunday
A74: TXN-00073 | B74: 45308 | C74: 11:15 | D74: Simran Malhotra | E74: CUST0337 | F74: Member | G74: Cheesecake | H74: Dessert | I74: Food | K74: 1 | L74: 190 | M74: 0.1 | N74: 190 | O74: 171 | P74: Cash | R74: Chandigarh | S74: Rahul | T74: Completed | U74: 5 | V74: 166 | W74: 21 | X74: 84.73 | Y74: 86.27 | Z74: Student Offer | AA74: Average | AB74: 190 | AC74: 19 | AD74: 171 | AE74: 84.73 | AF74: 86.27 | AG74: 2024 | AH74: 1 | AI74: Jan | AJ74: Wednesday
A75: TXN-00074 | B75: 45504 | C75: 15:30 | D75: Rahul Kaur | E75: CUST0365 | F75: Unknown | G75: Espresso | H75: Coffee | I75: Hot | J75: Large | K75: 3 | L75: 90 | M75: 0.1 | N75: 270 | O75: 243 | P75: Cash | R75: Ludhiana | S75: Simran | T75: Completed | U75: 5 | V75: 25 | W75: 42 | X75: 47.31 | Y75: 101.07 | Z75: Unknown | AA75: Excellent | AB75: 270 | AC75: 27 | AD75: 243 | AE75: 141.93 | AF75: 101.07 | AG75: 2024 | AH75: 7 | AI75: Jul | AJ75: Wednesday
A76: TXN-00075 | B76: 45372 | C76: 16:10 | D76: Arjun Mehta | E76: CUST0292 | F76: New Customer | G76: Muffin | H76: Bakery | I76: Food | J76: Large | K76: 1 | L76: 95 | M76: 0.05 | N76: 95 | O76: 90.25 | Q76: Walk-in | R76: Chandigarh | S76: Simran | T76: Pending | U76: 2 | V76: 333 | X76: 44.76 | Y76: 45.49 | Z76: Festive Offer | AA76: Average | AB76: 95 | AC76: 4.75 | AD76: 90.25 | AE76: 44.76 | AF76: 45.49 | AG76: 2024 | AH76: 3 | AI76: Mar | AJ76: Thursday
A77: TXN-00076 | B77: 45499 | C77: 18:45 | D77: Riya Mehta | E77: CUST0376 | F77: Member | G77: Cookies | H77: Bakery | I77: Food | J77: Large | K77: 1 | L77: 70 | M77: 0.05 | N77: 70 | O77: 66.5 | P77: Cash | Q77: Online | R77: Ludhiana | S77: Rohan | T77: Completed | U77: 5 | V77: 75 | W77: 21 | X77: 27.34 | Y77: 39.16 | Z77: Instagram | AA77: Unknown | AB77: 70 | AC77: 3.5 | AD77: 66.5 | AE77: 27.34 | AF77: 39.16 | AG77: 2024 | AH77: 7 | AI77: Jul | AJ77: Friday
A78: TXN-00077 | B78: 45401 | C78: 12:50 | D78: Priya Kaur | E78: CUST0218 | F78: Regular | G78: Cookies | H78: Bakery | I78: Food | J78: Small | K78: 1 | L78: 75 | M78: 0.15 | N78: 75 | O78: 63.75 | P78: UPI | Q78: Online | R78: Gurugram | S78: Ananya | T78: Completed | U78: 5 | V78: 144 | W78: 60 | X78: 24.64 | Y78: 39.11 | Z78: Festive Offer | AA78: Average | AB78: 75 | AC78: 11.25 | AD78: 63.75 | AE78: 24.64 | AF78: 39.11 | AG78: 2024 | AH78: 4 | AI78: Apr | AJ78: Friday
A79: TXN-00078 | B79: 45569 | C79: 20:20 | D79: Manish Singh | E79: CUST0198 | F79: New Customer | G79: Espresso | H79: Coffee | I79: Hot | J79: Medium | K79: 1 | L79: 100 | M79: 0.05 | N79: 100 | O79: 95 | Q79: Walk-in | R79: Chandigarh | S79: Rohan | T79: Completed | U79: 3 | V79: 166 | W79: 55 | X79: 51.54 | Y79: 43.46 | Z79: Unknown | AA79: Poor | AB79: 100 | AC79: 5 | AD79: 95 | AE79: 51.54 | AF79: 43.46 | AG79: 2024 | AH79: 10 | AI79: Oct | AJ79: Friday
A80: TXN-00079 | B80: 45499 | C80: 13:10 | D80: Sahil Kaur | E80: CUST0136 | F80: Regular | G80: Green Tea | H80: Tea | I80: Hot | J80: Medium | K80: 1 | L80: 95 | M80: 0.15 | N80: 95 | O80: 80.75 | P80: UPI | Q80: Delivery App | R80: Delhi | S80: Priya | T80: Completed | U80: 3 | V80: 123 | W80: 22 | X80: 49.66 | Y80: 31.09 | Z80: Instagram | AA80: Excellent | AB80: 95 | AC80: 14.25 | AD80: 80.75 | AE80: 49.66 | AF80: 31.09 | AG80: 2024 | AH80: 7 | AI80: Jul | AJ80: Friday
A81: TXN-00080 | B81: 45576 | C81: 12:00 | D81: Riya Bansal | E81: Unknown | F81: Unknown | G81: Americano | H81: Coffee | I81: Hot | J81: Small | K81: 5 | L81: 100 | M81: 0.05 | N81: 500 | O81: 475 | P81: Cash | Q81: Walk-in | R81: Chandigarh | S81: Rahul | T81: Cancelled | U81: 5 | V81: 237 | X81: 40.9 | Y81: 270.5 | Z81: Weekend Offer | AA81: Excellent | AB81: 500 | AC81: 25 | AD81: 475 | AE81: 204.5 | AF81: 270.5 | AG81: 2024 | AH81: 10 | AI81: Oct | AJ81: Friday
A82: TXN-00081 | B82: 45589 | C82: 19:10 | D82: Pooja Sharma | E82: CUST0129 | F82: Regular | G82: Cold Brew | H82: Coffee | I82: Cold | J82: Small | K82: 1 | L82: 160 | M82: 0.05 | N82: 160 | O82: 152 | P82: UPI | Q82: Walk-in | R82: Pune | S82: Simran | T82: Completed | U82: 5 | V82: 436 | W82: 17 | X82: 75.8 | Y82: 76.2 | Z82: Student Offer | AA82: Unknown | AB82: 160 | AC82: 8 | AD82: 152 | AE82: 75.8 | AF82: 76.2 | AG82: 2024 | AH82: 10 | AI82: Oct | AJ82: Thursday
A83: TXN-00082 | B83: 45553 | C83: 07:20 | D83: Karan Kapoor | E83: CUST0125 | F83: Member | G83: Latte | H83: Coffee | I83: Hot | J83: Medium | K83: 2 | L83: 120 | N83: 240 | P83: UPI | R83: Ludhiana | S83: Karan | T83: Cancelled | U83: 3 | V83: 379 | W83: 16 | X83: 42.74 | Z83: Instagram | AA83: Excellent | AB83: 240 | AC83: 0 | AD83: 240 | AE83: 85.48 | AF83: 154.52 | AG83: 2024 | AH83: 9 | AI83: Sep | AJ83: Wednesday
A84: TXN-00083 | B84: 45337 | C84: 07:45 | D84: Unknown | E84: CUST0166 | F84: Member | G84: Cookies | H84: Bakery | I84: Food | J84: Medium | K84: 1 | L84: 65 | N84: 65 | P84: Card | R84: Chandigarh | S84: Rohan | T84: Completed | U84: 3 | V84: 484 | W84: 21 | X84: 31.78 | Z84: Student Offer | AA84: Excellent | AB84: 65 | AC84: 0 | AD84: 65 | AE84: 31.78 | AF84: 33.22 | AG84: 2024 | AH84: 2 | AI84: Feb | AJ84: Thursday
A85: TXN-00084 | B85: 45652 | C85: 20:00 | D85: Priya Kapoor | E85: Unknown | F85: Member | G85: Espresso | H85: Coffee | I85: Hot | J85: Large | K85: 1 | L85: 85 | N85: 85 | P85: Cash | Q85: Online | R85: Chandigarh | S85: Karan | T85: Completed | U85: 5 | W85: 55 | X85: 36.48 | Z85: Weekend Offer | AA85: Poor | AB85: 85 | AC85: 0 | AD85: 85 | AE85: 36.48 | AF85: 48.52 | AG85: 2024 | AH85: 12 | AI85: Dec | AJ85: Thursday
A86: TXN-00085 | C86: 20:45 | D86: Vivaan Bansal | E86: CUST0337 | F86: Regular | G86: Muffin | H86: Bakery | I86: Food | J86: Small | K86: 3 | L86: 85 | M86: 0.1 | N86: 255 | O86: 229.5 | P86: Card | Q86: Online | R86: Ludhiana | S86: Neha | T86: Completed | U86: 3 | V86: 52 | X86: 36.8 | Y86: 119.1 | Z86: Student Offer | AA86: Poor | AB86: 255 | AC86: 25.5 | AD86: 229.5 | AE86: 110.4 | AF86: 119.1
A87: TXN-00086 | B87: 45314 | C87: 21:15 | D87: Nikhil Chopra | E87: CUST0398 | F87: Member | G87: Cold Brew | H87: Coffee | I87: Cold | J87: Small | K87: 1 | L87: 165 | M87: 0.05 | N87: 165 | O87: 156.75 | P87: Card | Q87: Online | R87: Pune | S87: Simran | T87: Completed | U87: 4 | V87: 258 | W87: 45 | X87: 62.6 | Y87: 94.15 | Z87: Unknown | AA87: Excellent | AB87: 165 | AC87: 8.25 | AD87: 156.75 | AE87: 62.6 | AF87: 94.15 | AG87: 2024 | AH87: 1 | AI87: Jan | AJ87: Tuesday
A88: TXN-00087 | B88: 45462 | C88: 20:15 | D88: Kavya Sharma | E88: CUST0244 | F88: Regular | G88: Espresso | H88: Coffee | I88: Hot | J88: Small | K88: 2 | L88: 90 | M88: 0.05 | N88: 180 | O88: 171 | P88: Card | Q88: Walk-in | R88: Ludhiana | S88: Karan | T88: Completed | U88: 4 | V88: 460 | W88: 58 | X88: 33.37 | Y88: 104.26 | Z88: Festive Offer | AA88: Unknown | AB88: 180 | AC88: 9 | AD88: 171 | AE88: 66.74 | AF88: 104.26 | AG88: 2024 | AH88: 6 | AI88: Jun | AJ88: Wednesday
A89: TXN-00088 | B89: 45332 | C89: 16:50 | D89: Aarav Malhotra | E89: Unknown | F89: Regular | G89: Americano | H89: Coffee | I89: Hot | J89: Small | K89: 1 | L89: 105 | M89: 0.05 | N89: 105 | O89: 99.75 | R89: Gurugram | S89: Simran | T89: Completed | U89: 5 | V89: 112 | W89: 21 | X89: 37.81 | Y89: 61.94 | Z89: Festive Offer | AA89: Poor | AB89: 105 | AC89: 5.25 | AD89: 99.75 | AE89: 37.81 | AF89: 61.94 | AG89: 2024 | AH89: 2 | AI89: Feb | AJ89: Saturday
A90: TXN-00089 | B90: 45653 | C90: 19:00 | D90: Riya Mehta | E90: CUST0247 | F90: Regular | G90: Green Tea | H90: Tea | I90: Hot | J90: Large | K90: 1 | L90: 95 | M90: 0 | O90: 95 | P90: Cash | Q90: Delivery App | R90: Pune | S90: Priya | T90: Completed | U90: 5 | V90: 133 | W90: 55 | X90: 40.81 | Y90: 54.19 | Z90: Unknown | AA90: Good | AB90: 95 | AC90: 0 | AD90: 95 | AE90: 40.81 | AF90: 54.19 | AG90: 2024 | AH90: 12 | AI90: Dec | AJ90: Friday
A91: TXN-00090 | B91: 45432 | C91: 20:50 | D91: Pooja Singh | E91: CUST0328 | F91: Member | G91: Iced Tea | H91: Tea | I91: Cold | J91: Medium | K91: 2 | L91: 115 | N91: 230 | P91: UPI | Q91: Walk-in | R91: Mohali | S91: Simran | T91: Completed | V91: 300 | X91: 48.1 | Z91: Instagram | AA91: Unknown | AB91: 230 | AC91: 0 | AD91: 230 | AE91: 96.2 | AF91: 133.8 | AG91: 2024 | AH91: 5 | AI91: May | AJ91: Monday
A92: TXN-00091 | B92: 45324 | C92: 09:10 | D92: Ananya Kaur | E92: CUST0231 | F92: Unknown | G92: Latte | H92: Coffee | I92: Hot | J92: Large | K92: 1 | L92: 130 | M92: 0.05 | N92: 130 | O92: 123.5 | P92: Cash | Q92: Online | R92: Mohali | S92: Karan | T92: Completed | U92: 3 | V92: 275 | W92: 54 | X92: 51.33 | Y92: 72.17 | Z92: Weekend Offer | AA92: Unknown | AB92: 130 | AC92: 6.5 | AD92: 123.5 | AE92: 51.33 | AF92: 72.17 | AG92: 2024 | AH92: 2 | AI92: Feb | AJ92: Friday
A93: TXN-00092 | B93: 45612 | C93: 21:20 | D93: Priya Mehta | E93: CUST0108 | F93: New Customer | G93: Masala Chai | H93: Tea | I93: Hot | J93: Medium | K93: 1 | L93: 75 | M93: 0 | N93: 75 | O93: 75 | Q93: Delivery App | R93: Gurugram | S93: Rohan | T93: Cancelled | U93: 3 | W93: 17 | X93: 45.27 | Y93: 29.73 | Z93: Festive Offer | AA93: Good | AB93: 75 | AC93: 0 | AD93: 75 | AE93: 45.27 | AF93: 29.73 | AG93: 2024 | AH93: 11 | AI93: Nov | AJ93: Saturday
A94: TXN-00093 | B94: 45405 | C94: 09:15 | D94: Vivaan Malhotra | E94: CUST0196 | F94: Unknown | G94: Americano | H94: Coffee | I94: Hot | K94: 1 | L94: 95 | M94: 0 | N94: 95 | O94: 95 | P94: Card | Q94: Online | R94: Gurugram | S94: Rohan | T94: Completed | U94: 1 | V94: 336 | W94: 22 | X94: 52.39 | Y94: 42.61 | Z94: Festive Offer | AA94: Excellent | AB94: 95 | AC94: 0 | AD94: 95 | AE94: 52.39 | AF94: 42.61 | AG94: 2024 | AH94: 4 | AI94: Apr | AJ94: Tuesday
A95: TXN-00094 | B95: 45398 | C95: 20:30 | D95: Isha Kapoor | E95: CUST0343 | F95: Unknown | G95: Cookies | H95: Bakery | I95: Food | J95: Small | K95: 1 | L95: 70 | M95: 0.15 | N95: 70 | O95: 59.5 | P95: UPI | Q95: Online | R95: Gurugram | S95: Rohan | T95: Completed | U95: 5 | V95: 247 | W95: 38 | X95: 36.84 | Y95: 22.66 | Z95: Festive Offer | AA95: Excellent | AB95: 70 | AC95: 10.5 | AD95: 59.5 | AE95: 36.84 | AF95: 22.66 | AG95: 2024 | AH95: 4 | AI95: Apr | AJ95: Tuesday
A96: TXN-00095 | B96: 45629 | C96: 12:30 | D96: Priya Chopra | E96: CUST0280 | F96: Unknown | G96: Cheesecake | H96: Dessert | I96: Food | J96: Small | K96: 1 | L96: 185 | M96: 0 | O96: 185 | P96: Card | Q96: Walk-in | R96: Bengaluru | S96: Neha | T96: Pending | U96: 5 | W96: 33 | X96: 101.49 | Y96: 83.51 | Z96: Student Offer | AA96: Average | AB96: 185 | AC96: 0 | AD96: 185 | AE96: 101.49 | AF96: 83.51 | AG96: 2024 | AH96: 12 | AI96: Dec | AJ96: Tuesday
A97: TXN-00096 | B97: 45440 | C97: 16:20 | D97: Isha Kaur | E97: CUST0256 | F97: Regular | G97: Americano | H97: Coffee | I97: Hot | J97: Small | K97: 1 | L97: 110 | M97: 0.15 | N97: 110 | O97: 93.5 | P97: UPI | Q97: Online | R97: Pune | S97: Ananya | T97: Completed | U97: 5 | W97: 51 | X97: 53.46 | Y97: 40.04 | Z97: Unknown | AA97: Excellent | AB97: 110 | AC97: 16.5 | AD97: 93.5 | AE97: 53.46 | AF97: 40.04 | AG97: 2024 | AH97: 5 | AI97: May | AJ97: Tuesday
A98: TXN-00097 | B98: 45460 | C98: 08:45 | D98: Aditya Kaur | E98: CUST0207 | F98: Regular | G98: Iced Tea | H98: Tea | I98: Cold | J98: Small | K98: 2 | L98: 110 | M98: 0 | N98: 220 | O98: 220 | P98: UPI | Q98: Online | R98: Ludhiana | S98: Priya | T98: Completed | V98: 168 | W98: 50 | X98: 44.91 | Y98: 130.18 | Z98: Instagram | AA98: Good | AB98: 220 | AC98: 0 | AD98: 220 | AE98: 89.82 | AF98: 130.18 | AG98: 2024 | AH98: 6 | AI98: Jun | AJ98: Monday
A99: TXN-00098 | C99: 14:10 | D99: Sneha Gupta | E99: CUST0281 | F99: Member | G99: Mocha | H99: Coffee | I99: Hot | J99: Large | K99: 2 | L99: 155 | N99: 310 | P99: Card | Q99: Delivery App | R99: Chandigarh | S99: Karan | T99: Pending | V99: 131 | W99: 19 | X99: 64.28 | Z99: Unknown | AA99: Poor | AB99: 310 | AC99: 0 | AD99: 310 | AE99: 128.56 | AF99: 181.44
A100: TXN-00099 | B100: 45603 | C100: 09:30 | D100: Simran Singh | E100: CUST0301 | F100: Member | G100: Cookies | H100: Bakery | I100: Food | J100: Medium | K100: 2 | L100: 65 | M100: 0.1 | N100: 130 | O100: 117 | Q100: Walk-in | R100: Pune | S100: Rohan | T100: Cancelled | U100: 4 | V100: 31 | X100: 34.28 | Y100: 48.44 | Z100: Instagram | AA100: Poor | AB100: 130 | AC100: 13 | AD100: 117 | AE100: 68.56 | AF100: 48.44 | AG100: 2024 | AH100: 11 | AI100: Nov | AJ100: Thursday
...

Sheet Data Quality
A1: DATA CLEANING REPORT
A2: Source | B2: Sheet1
A3: Rows reviewed | B3: 1600
A4: Rows in cleaned table | B4: 1600
A5: Exact duplicate rows removed | B5: 0
A6: Conflicting duplicate IDs retained | B6: 0
A7: Missing dates retained as blank | B7: 54
A8: Quantities safely inferred | B8: 50
A9: Blank categorical cells set to Unknown | B9: 689
A10: Financial formula columns rebuilt | B10: 8
A11: Date-derived columns rebuilt | B11: 4
A13: CLEANING RULE | B13: ACTION
A14: Original data | B14: Preserved unchanged on Sheet1
A15: Text | B15: Trimmed and repeated spaces removed
A16: Missing categories | B16: Standardized to Unknown
A17: Missing discount | B17: Standardized to 0%
A18: Quantity | B18: Inferred only when gross sales / unit price is an exact positive integer
A19: Financial fields | B19: Recalculated with live formulas
A20: Date fields | B20: Year, month, and day recalculated from Date
A21: Unrecoverable values | B21: Left blank rather than guessed
A23: IMPUTATION SUMMARY
A24: Field | B24: Replacement rule
A25: Date | B25: 54 blanks → dataset median date (25-Jun-2024)
A26: Quantity | B26: 55 originally missing: 50 exactly inferred from gross sales ÷ unit price; final 5 → product mode (1 item)
A27: Customer Rating | B27: 224 blanks → dataset median (3)
A28: Loyalty Points | B28: 131 blanks → dataset median (244)
A29: Delivery Minutes | B29: 409 blanks → channel median: Walk-in 34, Online 35, Delivery App 37, Unknown 36
A30: Dependent fields | B30: 231 dependent gaps recalculated automatically in gross/net sales, cost, profit, year, month, and day
A31: Visual marker | B31: Pale yellow cells in Cleaned Data identify values reconstructed from originally blank source fields

Sheet Cleaned Data
A1: Transaction ID | B1: Date | C1: Time | D1: Customer Name | E1: Customer ID | F1: Customer Type | G1: Product | H1: Category | I1: Temperature | J1: Size | K1: Quantity | L1: Unit Price | M1: Discount | N1: Gross Sales | O1: Net Sales | P1: Payment Method | Q1: Sales Channel | R1: Store Location | S1: Staff Name | T1: Order Status | U1: Customer Rating | V1: Loyalty Points | W1: Delivery Minutes | X1: Cost Per Item | Y1: Profit | Z1: Campaign | AA1: Feedback | AB1: Calculated Gross Sales | AC1: Discount Amount | AD1: Calculated Net Sales | AE1: Total Cost | AF1: Calculated Profit | AG1: Year | AH1: Month Number | AI1: Month | AJ1: Day
A2: TXN-00001 | B2: 45553 | C2: 0.43055556 | D2: Simran Gupta | E2: CUST0310 | F2: New Customer | G2: Cappuccino | H2: Coffee | I2: Hot | J2: Unknown | K2: 2 | L2: 130 | M2: 0 | N2: =IFERROR(K2*L2,"") -> 260 | O2: =IF(N2="","",N2*(1-IF(M2="",0,M2))) -> 260 | P2: Card | Q2: Walk-in | R2: Bengaluru | S2: Neha | T2: Completed | U2: 2 | V2: 233 | W2: 56 | X2: 56.78 | Y2: =IF(OR(O2="",K2="",X2=""),"",O2-K2*X2) -> 146.44 | Z2: Unknown | AA2: Excellent | AB2: =N2 -> 260 | AC2: =IF(N2="","",N2*IF(M2="",0,M2)) -> 0 | AD2: =O2 -> 260 | AE2: =IF(OR(K2="",X2=""),"",K2*X2) -> 113.56 | AF2: =Y2 -> 146.44 | AG2: =IF(B2="","",YEAR(B2)) -> 2024 | AH2: =IF(B2="","",MONTH(B2)) -> 9 | AI2: =IF(B2="","",TEXT(B2,"mmm")) -> Sep | AJ2: =IF(B2="","",TEXT(B2,"dddd")) -> Wednesday
A3: TXN-00002 | B3: 45517 | C3: 0.71875 | D3: Sneha Kaur | E3: CUST0395 | F3: Unknown | G3: Brownie | H3: Bakery | I3: Food | J3: Medium | K3: 1 | L3: 115 | M3: 0.05 | N3: =IFERROR(K3*L3,"") -> 115 | O3: =IF(N3="","",N3*(1-IF(M3="",0,M3))) -> 109.25 | P3: Card | Q3: Walk-in | R3: Bengaluru | S3: Rahul | T3: Completed | U3: 4 | V3: 304 | W3: 34 | X3: 59.12 | Y3: =IF(OR(O3="",K3="",X3=""),"",O3-K3*X3) -> 50.13 | Z3: Student Offer | AA3: Unknown | AB3: =N3 -> 115 | AC3: =IF(N3="","",N3*IF(M3="",0,M3)) -> 5.75 | AD3: =O3 -> 109.25 | AE3: =IF(OR(K3="",X3=""),"",K3*X3) -> 59.12 | AF3: =Y3 -> 50.13 | AG3: =IF(B3="","",YEAR(B3)) -> 2024 | AH3: =IF(B3="","",MONTH(B3)) -> 8 | AI3: =IF(B3="","",TEXT(B3,"mmm")) -> Aug | AJ3: =IF(B3="","",TEXT(B3,"dddd")) -> Tuesday
A4: TXN-00003 | B4: 45293 | C4: 0.41666667 | D4: Sahil Singh | E4: CUST0330 | F4: Member | G4: Cookies | H4: Bakery | I4: Food | J4: Medium | K4: 1 | L4: 70 | M4: 0 | N4: =IFERROR(K4*L4,"") -> 70 | O4: =IF(N4="","",N4*(1-IF(M4="",0,M4))) -> 70 | P4: Cash | Q4: Walk-in | R4: Mohali | S4: Karan | T4: Completed | U4: 3 | V4: 237 | W4: 34 | X4: 24.95 | Y4: =IF(OR(O4="",K4="",X4=""),"",O4-K4*X4) -> 45.05 | Z4: Weekend Offer | AA4: Poor | AB4: =N4 -> 70 | AC4: =IF(N4="","",N4*IF(M4="",0,M4)) -> 0 | AD4: =O4 -> 70 | AE4: =IF(OR(K4="",X4=""),"",K4*X4) -> 24.95 | AF4: =Y4 -> 45.05 | AG4: =IF(B4="","",YEAR(B4)) -> 2024 | AH4: =IF(B4="","",MONTH(B4)) -> 1 | AI4: =IF(B4="","",TEXT(B4,"mmm")) -> Jan | AJ4: =IF(B4="","",TEXT(B4,"dddd")) -> Tuesday
A5: TXN-00004 | B5: 45335 | C5: 0.38194444 | D5: Rahul Bansal | E5: CUST0134 | F5: Member | G5: Latte | H5: Coffee | I5: Hot | J5: Large | K5: 1 | L5: 120 | M5: 0.1 | N5: =IFERROR(K5*L5,"") -> 120 | O5: =IF(N5="","",N5*(1-IF(M5="",0,M5))) -> 108 | P5: Card | Q5: Unknown | R5: Ludhiana | S5: Priya | T5: Completed | U5: 2 | V5: 162 | W5: 36 | X5: 54.9 | Y5: =IF(OR(O5="",K5="",X5=""),"",O5-K5*X5) -> 53.1 | Z5: Unknown | AA5: Average | AB5: =N5 -> 120 | AC5: =IF(N5="","",N5*IF(M5="",0,M5)) -> 12 | AD5: =O5 -> 108 | AE5: =IF(OR(K5="",X5=""),"",K5*X5) -> 54.9 | AF5: =Y5 -> 53.1 | AG5: =IF(B5="","",YEAR(B5)) -> 2024 | AH5: =IF(B5="","",MONTH(B5)) -> 2 | AI5: =IF(B5="","",TEXT(B5,"mmm")) -> Feb | AJ5: =IF(B5="","",TEXT(B5,"dddd")) -> Tuesday
A6: TXN-00005 | B6: 45530 | C6: 0.8125 | D6: Sahil Chopra | E6: CUST0256 | F6: Unknown | G6: Iced Latte | H6: Coffee | I6: Cold | J6: Medium | K6: 1 | L6: 160 | M6: 0.1 | N6: =IFERROR(K6*L6,"") -> 160 | O6: =IF(N6="","",N6*(1-IF(M6="",0,M6))) -> 144 | P6: UPI | Q6: Walk-in | R6: Ludhiana | S6: Neha | T6: Completed | U6: 1 | V6: 476 | W6: 34 | X6: 57.6 | Y6: =IF(OR(O6="",K6="",X6=""),"",O6-K6*X6) -> 86.4 | Z6: Weekend Offer | AA6: Excellent | AB6: =N6 -> 160 | AC6: =IF(N6="","",N6*IF(M6="",0,M6)) -> 16 | AD6: =O6 -> 144 | AE6: =IF(OR(K6="",X6=""),"",K6*X6) -> 57.6 | AF6: =Y6 -> 86.4 | AG6: =IF(B6="","",YEAR(B6)) -> 2024 | AH6: =IF(B6="","",MONTH(B6)) -> 8 | AI6: =IF(B6="","",TEXT(B6,"mmm")) -> Aug | AJ6: =IF(B6="","",TEXT(B6,"dddd")) -> Monday
A7: TXN-00006 | B7: 45460 | C7: 0.50694444 | D7: Arjun Chopra | E7: CUST0120 | F7: New Customer | G7: Green Tea | H7: Tea | I7: Hot | J7: Small | K7: 2 | L7: 100 | M7: 0.05 | N7: =IFERROR(K7*L7,"") -> 200 | O7: =IF(N7="","",N7*(1-IF(M7="",0,M7))) -> 190 | P7: Cash | Q7: Walk-in | R7: Chandigarh | S7: Karan | T7: Completed | U7: 1 | V7: 200 | W7: 34 | X7: 43.82 | Y7: =IF(OR(O7="",K7="",X7=""),"",O7-K7*X7) -> 102.36 | Z7: Instagram | AA7: Good | AB7: =N7 -> 200 | AC7: =IF(N7="","",N7*IF(M7="",0,M7)) -> 10 | AD7: =O7 -> 190 | AE7: =IF(OR(K7="",X7=""),"",K7*X7) -> 87.64 | AF7: =Y7 -> 102.36 | AG7: =IF(B7="","",YEAR(B7)) -> 2024 | AH7: =IF(B7="","",MONTH(B7)) -> 6 | AI7: =IF(B7="","",TEXT(B7,"mmm")) -> Jun | AJ7: =IF(B7="","",TEXT(B7,"dddd")) -> Monday
A8: TXN-00007 | B8: 45468 | C8: 0.6875 | D8: Rohan Bansal | E8: CUST0377 | F8: Unknown | G8: Cookies | H8: Bakery | I8: Food | J8: Small | K8: 2 | L8: 70 | M8: 0 | N8: =IFERROR(K8*L8,"") -> 140 | O8: =IF(N8="","",N8*(1-IF(M8="",0,M8))) -> 140 | P8: Card | Q8: Walk-in | R8: Bengaluru | S8: Rahul | T8: Completed | U8: 1 | V8: 159 | W8: 47 | X8: 26.09 | Y8: =IF(OR(O8="",K8="",X8=""),"",O8-K8*X8) -> 87.82 | Z8: Instagram | AA8: Average | AB8: =N8 -> 140 | AC8: =IF(N8="","",N8*IF(M8="",0,M8)) -> 0 | AD8: =O8 -> 140 | AE8: =IF(OR(K8="",X8=""),"",K8*X8) -> 52.18 | AF8: =Y8 -> 87.82 | AG8: =IF(B8="","",YEAR(B8)) -> 2024 | AH8: =IF(B8="","",MONTH(B8)) -> 6 | AI8: =IF(B8="","",TEXT(B8,"mmm")) -> Jun | AJ8: =IF(B8="","",TEXT(B8,"dddd")) -> Tuesday
A9: TXN-00008 | B9: 45469 | C9: 0.60416667 | D9: Meera Malhotra | E9: CUST0197 | F9: Regular | G9: Americano | H9: Coffee | I9: Hot | J9: Medium | K9: 2 | L9: 100 | M9: 0.1 | N9: =IFERROR(K9*L9,"") -> 200 | O9: =IF(N9="","",N9*(1-IF(M9="",0,M9))) -> 180 | P9: Cash | Q9: Walk-in | R9: Ludhiana | S9: Ananya | T9: Completed | U9: 5 | V9: 158 | W9: 16 | X9: 40.53 | Y9: =IF(OR(O9="",K9="",X9=""),"",O9-K9*X9) -> 98.94 | Z9: Unknown | AA9: Poor | AB9: =N9 -> 200 | AC9: =IF(N9="","",N9*IF(M9="",0,M9)) -> 20 | AD9: =O9 -> 180 | AE9: =IF(OR(K9="",X9=""),"",K9*X9) -> 81.06 | AF9: =Y9 -> 98.94 | AG9: =IF(B9="","",YEAR(B9)) -> 2024 | AH9: =IF(B9="","",MONTH(B9)) -> 6 | AI9: =IF(B9="","",TEXT(B9,"mmm")) -> Jun | AJ9: =IF(B9="","",TEXT(B9,"dddd")) -> Wednesday
A10: TXN-00009 | B10: 45371 | C10: 0.59027778 | D10: Neha Malhotra | E10: CUST0395 | F10: Unknown | G10: Brownie | H10: Bakery | I10: Food | J10: Small | K10: 2 | L10: 120 | M10: 0 | N10: =IFERROR(K10*L10,"") -> 240 | O10: =IF(N10="","",N10*(1-IF(M10="",0,M10))) -> 240 | P10: Card | Q10: Delivery App | R10: Mohali | S10: Rahul | T10: Completed | U10: 5 | V10: 134 | W10: 37 | X10: 63.46 | Y10: =IF(OR(O10="",K10="",X10=""),"",O10-K10*X10) -> 113.08 | Z10: Unknown | AA10: Excellent | AB10: =N10 -> 240 | AC10: =IF(N10="","",N10*IF(M10="",0,M10)) -> 0 | AD10: =O10 -> 240 | AE10: =IF(OR(K10="",X10=""),"",K10*X10) -> 126.92 | AF10: =Y10 -> 113.08 | AG10: =IF(B10="","",YEAR(B10)) -> 2024 | AH10: =IF(B10="","",MONTH(B10)) -> 3 | AI10: =IF(B10="","",TEXT(B10,"mmm")) -> Mar | AJ10: =IF(B10="","",TEXT(B10,"dddd")) -> Wednesday
A11: TXN-00010 | B11: 45429 | C11: 0.70138889 | D11: Nikhil Gupta | E11: CUST0136 | F11: Regular | G11: Mocha | H11: Coffee | I11: Hot | J11: Small | K11: 1 | L11: 145 | M11: 0.05 | N11: =IFERROR(K11*L11,"") -> 145 | O11: =IF(N11="","",N11*(1-IF(M11="",0,M11))) -> 137.75 | P11: Card | Q11: Online | R11: Delhi | S11: Simran | T11: Completed | U11: 1 | V11: 352 | W11: 33 | X11: 86.8 | Y11: =IF(OR(O11="",K11="",X11=""),"",O11-K11*X11) -> 50.95 | Z11: Festive Offer | AA11: Average | AB11: =N11 -> 145 | AC11: =IF(N11="","",N11*IF(M11="",0,M11)) -> 7.25 | AD11: =O11 -> 137.75 | AE11: =IF(OR(K11="",X11=""),"",K11*X11) -> 86.8 | AF11: =Y11 -> 50.95 | AG11: =IF(B11="","",YEAR(B11)) -> 2024 | AH11: =IF(B11="","",MONTH(B11)) -> 5 | AI11: =IF(B11="","",TEXT(B11,"mmm")) -> May | AJ11: =IF(B11="","",TEXT(B11,"dddd")) -> Friday
A12: TXN-00011 | B12: 45477 | C12: 0.88194444 | D12: Kavya Verma | E12: CUST0394 | F12: Regular | G12: Mocha | H12: Coffee | I12: Hot | J12: Medium | K12: 1 | L12: 145 | M12: 0 | N12: =IFERROR(K12*L12,"") -> 145 | O12: =IF(N12="","",N12*(1-IF(M12="",0,M12))) -> 145 | P12: Cash | Q12: Walk-in | R12: Mohali | S12: Rahul | T12: Completed | U12: 1 | V12: 403 | W12: 52 | X12: 54.97 | Y12: =IF(OR(O12="",K12="",X12=""),"",O12-K12*X12) -> 90.03 | Z12: Weekend Offer | AA12: Good | AB12: =N12 -> 145 | AC12: =IF(N12="","",N12*IF(M12="",0,M12)) -> 0 | AD12: =O12 -> 145 | AE12: =IF(OR(K12="",X12=""),"",K12*X12) -> 54.97 | AF12: =Y12 -> 90.03 | AG12: =IF(B12="","",YEAR(B12)) -> 2024 | AH12: =IF(B12="","",MONTH(B12)) -> 7 | AI12: =IF(B12="","",TEXT(B12,"mmm")) -> Jul | AJ12: =IF(B12="","",TEXT(B12,"dddd")) -> Thursday
A13: TXN-00012 | B13: 45565 | C13: 0.36805556 | D13: Isha Chopra | E13: CUST0312 | F13: Regular | G13: Cold Brew | H13: Coffee | I13: Cold | J13: Medium | K13: 1 | L13: 160 | M13: 0.05 | N13: =IFERROR(K13*L13,"") -> 160 | O13: =IF(N13="","",N13*(1-IF(M13="",0,M13))) -> 152 | P13: UPI | Q13: Delivery App | R13: Bengaluru | S13: Rohan | T13: Completed | U13: 5 | V13: 99 | W13: 12 | X13: 93.45 | Y13: =IF(OR(O13="",K13="",X13=""),"",O13-K13*X13) -> 58.55 | Z13: Instagram | AA13: Average | AB13: =N13 -> 160 | AC13: =IF(N13="","",N13*IF(M13="",0,M13)) -> 8 | AD13: =O13 -> 152 | AE13: =IF(OR(K13="",X13=""),"",K13*X13) -> 93.45 | AF13: =Y13 -> 58.55 | AG13: =IF(B13="","",YEAR(B13)) -> 2024 | AH13: =IF(B13="","",MONTH(B13)) -> 9 | AI13: =IF(B13="","",TEXT(B13,"mmm")) -> Sep | AJ13: =IF(B13="","",TEXT(B13,"dddd")) -> Monday
... A1601: TXN-01600 | B1601: 45322 | C1601: 0.73958333 | D1601: Neha Singh | E1601: CUST0251 | F1601: Unknown | G1601: Latte | H1601: Coffee | I1601: Hot | J1601: Large | K1601: 1 | L1601: 120 | M1601: 0 | N1601: =IFERROR(K1601*L1601,"") -> 120 | O1601: =IF(N1601="","",N1601*(1-IF(M1601="",0,M1601))) -> 120 | P1601: Card | Q1601: Walk-in | R1601: Chandigarh | S1601: Aarav | T1601: Completed | U1601: 3 | V1601: 498 | W1601: 29 | X1601: 60.22 | Y1601: =IF(OR(O1601="",K1601="",X1601=""),"",O1601-K1601*X1601) -> 59.78 | Z1601: Weekend Offer | AA1601: Good | AB1601: =N1601 -> 120 | AC1601: =IF(N1601="","",N1601*IF(M1601="",0,M1601)) -> 0 | AD1601: =O1601 -> 120 | AE1601: =IF(OR(K1601="",X1601=""),"",K1601*X1601) -> 60.22 | AF1601: =Y1601 -> 59.78 | AG1601: =IF(B1601="","",YEAR(B1601)) -> 2024 | AH1601: =IF(B1601="","",MONTH(B1601)) -> 1 | AI1601: =IF(B1601="","",TEXT(B1601,"mmm")) -> Jan | AJ1601: =IF(B1601="","",TEXT(B1601,"dddd")) -> Wednesday

Sheet Pivot Analysis
A1: BUSINESS PERFORMANCE — PIVOT ANALYSIS
A3: MONTHLY PERFORMANCE | H3: CATEGORY PERFORMANCE | N3: PRODUCT PERFORMANCE | V3: LOCATION PERFORMANCE
A5: Month | B5: Total Net Sales | C5: Total Profit | D5: Orders | E5: Units | H5: Category | I5: Total Net Sales | J5: Total Profit | K5: Units | L5: Average of Customer Rating | N5: Product | O5: Total Net Sales | P5: Total Profit | Q5: Orders | R5: Units | V5: Store Location | W5: Total Net Sales | X5: Total Profit | Y5: Orders | Z5: Average of Delivery Minutes
A6: Jan | B6: 26205.75 | C6: 13644.09 | D6: 140 | E6: 224 | H6: Bakery | I6: 64160.75 | J6: 32524.94 | K6: 705 | L6: 3.4133017 | N6: Americano | O6: 15288.25 | P6: 7716.11 | Q6: 91 | R6: 158 | V6: Bengaluru | W6: 43703.5 | X6: 21830.91 | Y6: 242 | Z6: 34.041322
A7: Feb | B7: 23017.5 | C7: 11738.31 | D7: 116 | E7: 200 | H7: Coffee | I7: 148718.75 | J7: 75411.85 | K7: 1207 | L7: 3.2582026 | N7: Brownie | O7: 19715.5 | P7: 9828.59 | Q7: 100 | R7: 171 | V7: Chandigarh | W7: 49120.75 | X7: 25448.92 | Y7: 225 | Z7: 34.555556
A8: Mar | B8: 28172.75 | C8: 13916.57 | D8: 141 | E8: 246 | H8: Dessert | I8: 25950.5 | J8: 13291.75 | K8: 143 | L8: 2.9450549 | N8: Cappuccino | O8: 22526.5 | P8: 11688.69 | Q8: 98 | R8: 178 | V8: Delhi | W8: 41779.75 | X8: 21762.4 | Y8: 218 | Z8: 34.922018
A9: Apr | B9: 24501.25 | C9: 12577.57 | D9: 126 | E9: 199 | H9: Food | I9: 28758 | J9: 14302.59 | K9: 166 | L9: 3.1770833 | N9: Cheesecake | O9: 25950.5 | P9: 13291.75 | Q9: 91 | R9: 143 | V9: Gurugram | W9: 44104.75 | X9: 22373.67 | Y9: 225 | Z9: 34.564444
A10: May | B10: 26799 | C10: 13484.02 | D10: 145 | E10: 240 | H10: Tea | I10: 43504.5 | J10: 22486.68 | K10: 472 | L10: 3.3745704 | N10: Cold Brew | O10: 27844.5 | P10: 13683.16 | Q10: 108 | R10: 182 | V10: Ludhiana | W10: 41601.5 | X10: 21281.38 | Y10: 222 | Z10: 36.693694
A11: Jun | B11: 39701 | C11: 19924.86 | D11: 190 | E11: 343 | N11: Cookies | O11: 13444.5 | P11: 7009.01 | Q11: 114 | R11: 197 | V11: Mohali | W11: 41910.25 | X11: 21088.97 | Y11: 216 | Z11: 35.800926
A12: Jul | B12: 20692.75 | C12: 10424.42 | D12: 108 | E12: 177 | N12: Croissant | O12: 15309 | P12: 7662.9 | Q12: 96 | R12: 157 | V12: Pune | W12: 48872 | X12: 24231.56 | Y12: 252 | Z12: 34.694444
A13: Aug | B13: 26761.75 | C13: 13688.3 | D13: 131 | E13: 231 | N13: Espresso | O13: 15349.75 | P13: 7896.8 | Q13: 103 | R13: 179
A14: Sep | B14: 22288 | C14: 11174.92 | D14: 116 | E14: 198 | N14: Green Tea | O14: 12956.25 | P14: 6819.19 | Q14: 90 | R14: 139
A15: Oct | B15: 21279.5 | C15: 11025.97 | D15: 114 | E15: 183 | N15: Iced Latte | O15: 21165.25 | P15: 10789.36 | Q15: 93 | R15: 148
A16: Nov | B16: 23978 | C16: 12458.1 | D16: 126 | E16: 212 | N16: Iced Tea | O16: 17533 | P16: 8908.52 | Q16: 102 | R16: 166
A17: Dec | B17: 27695.25 | C17: 13960.68 | D17: 147 | E17: 240 | N17: Latte | O17: 19876 | P17: 10091.22 | Q17: 102 | R17: 171
N18: Masala Chai | O18: 13015.25 | P18: 6758.97 | Q18: 99 | R18: 167
N19: Mocha | O19: 26668.5 | P19: 13546.51 | Q19: 106 | R19: 191
N20: Muffin | O20: 15691.75 | P20: 8024.44 | Q20: 111 | R20: 180
N21: Sandwich | O21: 28758 | P21: 14302.59 | Q21: 96 | R21: 166
A26: CHANNEL PERFORMANCE | H26: PAYMENT MIX | N26: CAMPAIGN PERFORMANCE | V26: STAFF PERFORMANCE
A28: Sales Channel | B28: Total Net Sales | C28: Total Profit | D28: Orders | E28: Average of Delivery Minutes | H28: Payment Method | I28: Total Net Sales | J28: Orders | K28: Total Profit | N28: Campaign | O28: Total Net Sales | P28: Total Profit | Q28: Orders | R28: Average of Customer Rating | V28: Staff Name | W28: Total Net Sales | X28: Total Profit | Y28: Orders | Z28: Average of Customer Rating
A29: Delivery App | B29: 54947.25 | C29: 27477.31 | D29: 274 | E29: 35.587591 | H29: Card | I29: 115649.75 | J29: 578 | K29: 58529.51 | N29: Festive Offer | O29: 38381 | P29: 19258.16 | Q29: 205 | R29: 3.1268293 | V29: Aarav | W29: 37451 | X29: 18747.66 | Y29: 191 | Z29: 3.3350785
A30: Online | B30: 102136.75 | C30: 51184.16 | D30: 534 | E30: 35.205993 | H30: Cash | I30: 61214.25 | J30: 324 | K30: 31377.61 | N30: Instagram | O30: 95471.25 | P30: 48310.93 | Q30: 491 | R30: 3.3625255 | V30: Ananya | W30: 43057.5 | X30: 21681.38 | Y30: 214 | Z30: 3.2476636
A31: Unknown | B31: 62501.5 | C31: 32152.27 | D31: 303 | E31: 35.590759 | H31: Unknown | I31: 32480.5 | J31: 162 | K31: 16685.35 | N31: None | O31: 2331.75 | P31: 1156.61 | Q31: 11 | R31: 3.6363636 | V31: Karan | W31: 38292.25 | X31: 19753.81 | Y31: 204 | Z31: 3.3284314
A32: Walk-in | B32: 91507 | C32: 47204.07 | D32: 489 | E32: 34.130879 | H32: UPI | I32: 101748 | J32: 536 | K32: 51425.34 | N32: Student Offer | O32: 48231.5 | P32: 24733.36 | Q32: 236 | R32: 3.3305085 | V32: Neha | W32: 37494.5 | X32: 19344.58 | Y32: 198 | Z32: 3.2525253
N33: Unknown | O33: 80353.5 | P33: 41168.17 | Q33: 429 | R33: 3.2610723 | V33: Priya | W33: 33905.75 | X33: 17131.83 | Y33: 183 | Z33: 3.3606557
N34: Weekend Offer | O34: 46323.5 | P34: 23390.58 | Q34: 228 | R34: 3.3289474 | V34: Rahul | W34: 39792.75 | X34: 20007.9 | Y34: 186 | Z34: 3.2741935
V35: Rohan | W35: 39083.25 | X35: 19880.78 | Y35: 211 | Z35: 3.3838863
V36: Simran | W36: 42015.5 | X36: 21469.87 | Y36: 213 | Z36: 3.2065728
A43: CUSTOMER SEGMENTS | H43: ORDER STATUS | N43: RATING DISTRIBUTION | V43: FEEDBACK ANALYSIS
A45: Customer Type | B45: Total Net Sales | C45: Total Profit | D45: Orders | E45: Average of Customer Rating | H45: Order Status | I45: Total Net Sales | J45: Total Profit | K45: Orders | N45: Customer Rating | O45: Orders | P45: Total Net Sales | V45: Feedback | W45: Orders | X45: Total Net Sales | Y45: Average of Customer Rating
A46: Member | B46: 105480.5 | C46: 53795.1 | D46: 535 | E46: 3.2971963 | H46: Cancelled | I46: 52648.5 | J46: 26838.75 | K46: 263 | N46: 1 | O46: 206 | P46: 40607.5 | V46: Average | W46: 285 | X46: 52201.25 | Y46: 3.2912281
A47: New Customer | B47: 49924.75 | C47: 25201.53 | D47: 255 | E47: 3.1843137 | H47: Completed | I47: 203344.25 | J47: 103283.95 | K47: 1076 | N47: 2 | O47: 244 | P47: 50013.5 | V47: Excellent | W47: 520 | X47: 103283.5 | Y47: 3.3134615
A48: Regular | B48: 104515.75 | C48: 52854.34 | D48: 544 | E48: 3.3970588 | H48: Pending | I48: 55099.75 | J48: 27895.11 | K48: 261 | N48: 3 | O48: 466 | P48: 87158 | V48: Good | W48: 272 | X48: 53375.75 | Y48: 3.3272059
A49: Unknown | B49: 51171.5 | C49: 26166.84 | D49: 266 | E49: 3.2030075 | N49: 4 | O49: 236 | P49: 45494.5 | V49: Poor | W49: 271 | X49: 52207.5 | Y49: 3.2250923
N50: 5 | O50: 448 | P50: 87819 | V50: Unknown | W50: 252 | X50: 50024.5 | Y50: 3.3174603
A53: Row Labels | B53: Sum of Net Sales
A54: Bengaluru | B54: 43703.5
A55: Jan | B55: 4493
A56: Feb | B56: 2102.5
A57: Mar | B57: 3707.5
A58: Apr | B58: 3521.75
A59: May | B59: 4670.25
A60: Jun | B60: 6919.5
A61: Jul | B61: 3456.5
A62: Aug | B62: 3450.5
A63: Sep | B63: 2137.5
A64: Oct | B64: 1522.5
A65: Nov | B65: 3996.75
... A145: Grand Total | B145: 311092.5

Sheet Charts
B1: DashBoard
B2: Performance Overview 2023-2024
B4: NET Gross KpIs | F4: Loyalty Point KpIs | K4: Total Cost KpIs | P4: NET Profit KpIs | T4: NET SALES KpIs
B8: =SUM('Cleaned Data'!N:N) -> 328085 | F8: =SUM('Cleaned Data'!V:V) -> 394462 | K8: =SUM('Cleaned Data'!AE:AE) -> 153074.69 | P8: =SUM('Cleaned Data'!AF:AF) -> 158017.81 | T8: =SUM('Cleaned Data'!O:O) -> 311092.5
